{"version":"3.10.1","examples":[{"id":"./spec/client_spec.rb[1:1:1]","description":"requires an argument","full_description":"OxfordDictionary::Client#new requires an argument","status":"passed","file_path":"./spec/client_spec.rb","line_number":11,"run_time":0.002401,"pending_message":null},{"id":"./spec/client_spec.rb[1:1:2]","description":"requires a hash argument","full_description":"OxfordDictionary::Client#new requires a hash argument","status":"passed","file_path":"./spec/client_spec.rb","line_number":16,"run_time":0.000177,"pending_message":null},{"id":"./spec/client_spec.rb[1:1:3]","description":"requires both id and key","full_description":"OxfordDictionary::Client#new requires both id and key","status":"passed","file_path":"./spec/client_spec.rb","line_number":21,"run_time":7.3e-05,"pending_message":null},{"id":"./spec/client_spec.rb[1:2:1:1]","description":"calls the Entries endpoint with correct arguments","full_description":"OxfordDictionary::Client#entry when the argument is a Hash calls the Entries endpoint with correct arguments","status":"passed","file_path":"./spec/client_spec.rb","line_number":33,"run_time":0.011199,"pending_message":null},{"id":"./spec/client_spec.rb[1:3:1]","description":"calls the Lemmas endpoint with correct arguments","full_description":"OxfordDictionary::Client#lemma calls the Lemmas endpoint with correct arguments","status":"passed","file_path":"./spec/client_spec.rb","line_number":51,"run_time":0.000363,"pending_message":null},{"id":"./spec/client_spec.rb[1:4:1]","description":"calls the Translations endpoint with correct arguments","full_description":"OxfordDictionary::Client#translation calls the Translations endpoint with correct arguments","status":"passed","file_path":"./spec/client_spec.rb","line_number":75,"run_time":0.000303,"pending_message":null},{"id":"./spec/client_spec.rb[1:5:1]","description":"calls the Sentences endpoint with correct arguments","full_description":"OxfordDictionary::Client#sentence calls the Sentences endpoint with correct arguments","status":"passed","file_path":"./spec/client_spec.rb","line_number":93,"run_time":0.000376,"pending_message":null},{"id":"./spec/client_spec.rb[1:6:1]","description":"calls the Thesaurus endpoint with correct arguments","full_description":"OxfordDictionary::Client#thesaurus calls the Thesaurus endpoint with correct arguments","status":"passed","file_path":"./spec/client_spec.rb","line_number":108,"run_time":0.000346,"pending_message":null},{"id":"./spec/client_spec.rb[1:7:1]","description":"calls the Search endpoint with correct arguments","full_description":"OxfordDictionary::Client#search calls the Search endpoint with correct arguments","status":"passed","file_path":"./spec/client_spec.rb","line_number":122,"run_time":0.000374,"pending_message":null},{"id":"./spec/client_spec.rb[1:8:1]","description":"calls the Search endpoint with correct arguments","full_description":"OxfordDictionary::Client#search_translation calls the Search endpoint with correct arguments","status":"passed","file_path":"./spec/client_spec.rb","line_number":143,"run_time":0.000511,"pending_message":null},{"id":"./spec/deserialize_spec.rb[1:1:1]","description":"parses the JSON into an OpenStruct","full_description":"OxfordDictionary::Deserialize#call parses the JSON into an OpenStruct","status":"passed","file_path":"./spec/deserialize_spec.rb","line_number":11,"run_time":0.001062,"pending_message":null},{"id":"./spec/endpoints/entries_spec.rb[1:1:1]","description":"calls API as expected","full_description":"OxfordDictionary::Endpoints::Entries#entry calls API as expected","status":"passed","file_path":"./spec/endpoints/entries_spec.rb","line_number":22,"run_time":0.010314,"pending_message":null},{"id":"./spec/endpoints/entries_spec.rb[1:1:2:1]","description":"only returns entries that are verbs","full_description":"OxfordDictionary::Endpoints::Entries#entry when the params include lexicalCategory: verb only returns entries that are verbs","status":"passed","file_path":"./spec/endpoints/entries_spec.rb","line_number":37,"run_time":0.003925,"pending_message":null},{"id":"./spec/endpoints/entries_spec.rb[1:1:3:1]","description":"calls the API with en-us in the URL","full_description":"OxfordDictionary::Endpoints::Entries#entry when the dataset is en-us calls the API with en-us in the URL","status":"passed","file_path":"./spec/endpoints/entries_spec.rb","line_number":61,"run_time":0.0049,"pending_message":null},{"id":"./spec/endpoints/lemmas_spec.rb[1:1:1]","description":"calls API as expected","full_description":"OxfordDictionary::Endpoints::Lemmas#lemma calls API as expected","status":"passed","file_path":"./spec/endpoints/lemmas_spec.rb","line_number":22,"run_time":0.004029,"pending_message":null},{"id":"./spec/endpoints/lemmas_spec.rb[1:1:2:1]","description":"only returns lemmas that are verbs","full_description":"OxfordDictionary::Endpoints::Lemmas#lemma when the params include lexicalCategory: verb only returns lemmas that are verbs","status":"passed","file_path":"./spec/endpoints/lemmas_spec.rb","line_number":37,"run_time":0.008326,"pending_message":null},{"id":"./spec/endpoints/lemmas_spec.rb[1:1:3:1]","description":"calls the API with en-us in the URL","full_description":"OxfordDictionary::Endpoints::Lemmas#lemma when the language is es calls the API with en-us in the URL","status":"passed","file_path":"./spec/endpoints/lemmas_spec.rb","line_number":62,"run_time":0.0032,"pending_message":null},{"id":"./spec/endpoints/search_spec.rb[1:1:1]","description":"calls API as expected","full_description":"OxfordDictionary::Endpoints::Search#search calls API as expected","status":"passed","file_path":"./spec/endpoints/search_spec.rb","line_number":29,"run_time":0.000422,"pending_message":null},{"id":"./spec/endpoints/search_spec.rb[1:2:1]","description":"calls API as expected","full_description":"OxfordDictionary::Endpoints::Search#search_translation calls API as expected","status":"passed","file_path":"./spec/endpoints/search_spec.rb","line_number":61,"run_time":0.000287,"pending_message":null},{"id":"./spec/endpoints/sentences_spec.rb[1:1:1]","description":"calls API as expected","full_description":"OxfordDictionary::Endpoints::Sentences#sentence calls API as expected","status":"passed","file_path":"./spec/endpoints/sentences_spec.rb","line_number":30,"run_time":0.000358,"pending_message":null},{"id":"./spec/endpoints/thesaurus_spec.rb[1:1:1]","description":"calls API as expected","full_description":"OxfordDictionary::Endpoints::Thesaurus#thesaurus calls API as expected","status":"passed","file_path":"./spec/endpoints/thesaurus_spec.rb","line_number":30,"run_time":0.000396,"pending_message":null},{"id":"./spec/endpoints/translations_spec.rb[1:1:1]","description":"calls API as expected","full_description":"OxfordDictionary::Endpoints::Translations#translation calls API as expected","status":"passed","file_path":"./spec/endpoints/translations_spec.rb","line_number":36,"run_time":0.000337,"pending_message":null},{"id":"./spec/endpoints/translations_spec.rb[1:1:2:1]","description":"only returns strict match translations","full_description":"OxfordDictionary::Endpoints::Translations#translation when the params include strictMatch: true only returns strict match translations","status":"passed","file_path":"./spec/endpoints/translations_spec.rb","line_number":59,"run_time":0.000362,"pending_message":null},{"id":"./spec/oxford_dictionary_spec.rb[1:1]","description":"has a version number","full_description":"OxfordDictionary has a version number","status":"passed","file_path":"./spec/oxford_dictionary_spec.rb","line_number":4,"run_time":0.001119,"pending_message":null},{"id":"./spec/request_spec.rb[1:1:1]","description":"GETs a page correctly","full_description":"OxfordDictionary::Request#get GETs a page correctly","status":"passed","file_path":"./spec/request_spec.rb","line_number":24,"run_time":0.000624,"pending_message":null}],"summary":{"duration":0.061477,"example_count":25,"failure_count":0,"pending_count":0,"errors_outside_of_examples_count":0},"summary_line":"25 examples, 0 failures"}